aevion_verify/__init__.py
aevion_verify-1.0.0.dist-info/METADATA
aevion_verify-1.0.0.dist-info/WHEEL
aevion_verify-1.0.0.dist-info/top_level.txt
aevion_verify-1.0.0.dist-info/RECORD
