Metadata-Version: 2.4
Name: aevion-verify
Version: 1.0.0
Summary: Zero-dependency cryptographic verification for Aevion AI proofs
Author-email: Aevion LLC <opensource@aevion.ai>
License-Expression: MIT
Project-URL: Homepage, https://aevion.ai
Project-URL: Documentation, https://docs.aevion.ai
Project-URL: Repository, https://github.com/Aevion-ai/aevion-verify-py
Project-URL: Bug Tracker, https://github.com/Aevion-ai/aevion-verify-py/issues
Keywords: aevion,ai,verification,cryptography,ed25519,proof
Classifier: Development Status :: 5 - Production/Stable
Classifier: Intended Audience :: Developers
Classifier: Programming Language :: Python :: 3
Classifier: Programming Language :: Python :: 3.8
Classifier: Programming Language :: Python :: 3.9
Classifier: Programming Language :: Python :: 3.10
Classifier: Programming Language :: Python :: 3.11
Classifier: Programming Language :: Python :: 3.12
Classifier: Topic :: Security :: Cryptography
Classifier: Topic :: Software Development :: Libraries :: Python Modules
Requires-Python: >=3.8
Requires-Dist: cryptography>=41.0.0
Requires-Dist: requests>=2.31.0
